{
  "$schema": "http://json-schema.org/draft-07/schema#",
  "$ref": "#/definitions/OrgLogoutResult",
  "definitions": {
    "OrgLogoutResult": {
      "type": "object",
      "properties": {
        "success": {
          "type": "boolean"
        },
        "username": {
          "type": "string"
        }
      },
      "required": ["success", "username"],
      "additionalProperties": false,
      "description": "A list of account and environment names that were successfully logged out."
    }
  }
}
